{"1":{"children":{"2":{"children":{}},"6":{"children":{"8":{"children":{"10":{"children":{}}}},"14":{"children":{"16":{"children":{}},"20":{"children":{}},"24":{"children":{}}}},"28":{"children":{"30":{"children":{}},"34":{"children":{}},"38":{"children":{}}}},"42":{"children":{"44":{"children":{}},"48":{"children":{}},"52":{"children":{}}}},"56":{"children":{"58":{"children":{}},"62":{"children":{}},"66":{"children":{}}}},"70":{"children":{"72":{"children":{}},"76":{"children":{}},"80":{"children":{}}}},"84":{"children":{"86":{"children":{}},"90":{"children":{}},"94":{"children":{}}}},"98":{"children":{"100":{"children":{}},"104":{"children":{}},"108":{"children":{}}}},"112":{"children":{"114":{"children":{}},"118":{"children":{}},"122":{"children":{}}}},"126":{"children":{"128":{"children":{}},"132":{"children":{}},"136":{"children":{}}}},"140":{"children":{"142":{"children":{}},"146":{"children":{}},"150":{"children":{}}}}}}}},"154":{"children":{"155":{"children":{}},"158":{"children":{}},"161":{"children":{}},"164":{"children":{}},"167":{"children":{}},"170":{"children":{}},"174":{"children":{}},"178":{"children":{}},"183":{"children":{}},"187":{"children":{}},"192":{"children":{}},"195":{"children":{}},"199":{"children":{}},"203":{"children":{}},"211":{"children":{}},"216":{"children":{}},"224":{"children":{}},"228":{"children":{}},"232":{"children":{}},"240":{"children":{}},"249":{"children":{}},"258":{"children":{}},"261":{"children":{}},"265":{"children":{}},"268":{"children":{}},"272":{"children":{}},"275":{"children":{}},"278":{"children":{}},"282":{"children":{}},"290":{"children":{}},"293":{"children":{}},"296":{"children":{}},"299":{"children":{}},"300":{"children":{}},"301":{"children":{}},"304":{"children":{}}}},"307":{"children":{"308":{"children":{}},"314":{"children":{}}}},"315":{"children":{"316":{"children":{}},"319":{"children":{}},"322":{"children":{}},"326":{"children":{}},"330":{"children":{"332":{"children":{}},"333":{"children":{}},"334":{"children":{}},"335":{"children":{}},"336":{"children":{}},"337":{"children":{}}}},"338":{"children":{"339":{"children":{}},"340":{"children":{}},"341":{"children":{}}}},"342":{"children":{"343":{"children":{}},"344":{"children":{}},"345":{"children":{}}}}}},"346":{"children":{"347":{"children":{}},"350":{"children":{}},"353":{"children":{}},"356":{"children":{}},"359":{"children":{}},"362":{"children":{}}}},"365":{"children":{"366":{"children":{}},"374":{"children":{}},"382":{"children":{}},"385":{"children":{}},"388":{"children":{}},"396":{"children":{}},"399":{"children":{}}}},"403":{"children":{"404":{"children":{}},"406":{"children":{}},"409":{"children":{}},"413":{"children":{}}}},"416":{"children":{"417":{"children":{}},"420":{"children":{}},"423":{"children":{}},"427":{"children":{}},"431":{"children":{}},"435":{"children":{}},"439":{"children":{}}}},"448":{"children":{"449":{"children":{}},"453":{"children":{}},"456":{"children":{}},"461":{"children":{}},"466":{"children":{}},"469":{"children":{}},"473":{"children":{}},"478":{"children":{}}}},"481":{"children":{"482":{"children":{}},"491":{"children":{}},"498":{"children":{}},"504":{"children":{}},"511":{"children":{}},"521":{"children":{}},"530":{"children":{}},"536":{"children":{}},"546":{"children":{}},"556":{"children":{}},"563":{"children":{}},"578":{"children":{}},"581":{"children":{}},"592":{"children":{}},"600":{"children":{}},"602":{"children":{}},"608":{"children":{}},"618":{"children":{}},"633":{"children":{}},"661":{"children":{}},"689":{"children":{}}}},"694":{"children":{"1637":{"children":{}},"1638":{"children":{}},"1639":{"children":{}},"1640":{"children":{}},"1641":{"children":{}},"1642":{"children":{}},"1643":{"children":{}},"1644":{"children":{}},"1645":{"children":{}},"1646":{"children":{}},"1647":{"children":{}},"1648":{"children":{}},"1649":{"children":{}},"1650":{"children":{}},"1651":{"children":{}},"1652":{"children":{}},"1653":{"children":{}},"1654":{"children":{}},"1655":{"children":{}},"1656":{"children":{}},"1657":{"children":{}},"1658":{"children":{}},"1659":{"children":{}},"1660":{"children":{}},"1661":{"children":{}},"1662":{"children":{}},"1663":{"children":{}},"1664":{"children":{}},"1665":{"children":{}},"1666":{"children":{}},"1667":{"children":{}},"1668":{"children":{}},"1669":{"children":{}},"1670":{"children":{}},"1671":{"children":{}},"1672":{"children":{}},"1673":{"children":{}},"1674":{"children":{}},"1675":{"children":{}},"1676":{"children":{}},"1677":{"children":{}},"1678":{"children":{}},"1679":{"children":{}},"1680":{"children":{}},"1681":{"children":{}},"1682":{"children":{}},"1683":{"children":{}},"1684":{"children":{}},"1685":{"children":{}},"1686":{"children":{}},"1687":{"children":{}},"1688":{"children":{}},"1689":{"children":{}},"1690":{"children":{}},"1691":{"children":{}},"1692":{"children":{}},"1693":{"children":{}},"1694":{"children":{}},"1695":{"children":{}},"1696":{"children":{}},"1697":{"children":{}},"1698":{"children":{}},"1699":{"children":{}},"1700":{"children":{}},"1701":{"children":{}},"1702":{"children":{}},"1703":{"children":{}},"1704":{"children":{}},"1705":{"children":{}},"1706":{"children":{}},"1707":{"children":{}},"1708":{"children":{}},"1709":{"children":{}},"1710":{"children":{}},"1711":{"children":{}},"1712":{"children":{}},"1713":{"children":{}},"1714":{"children":{}},"1715":{"children":{}},"1716":{"children":{}},"1717":{"children":{}},"1718":{"children":{}},"1719":{"children":{}},"1720":{"children":{}},"1721":{"children":{}},"1722":{"children":{}},"1723":{"children":{}},"1724":{"children":{}},"1725":{"children":{}},"1726":{"children":{}},"1727":{"children":{}},"1728":{"children":{}},"1729":{"children":{}},"1730":{"children":{}},"1731":{"children":{}},"1732":{"children":{}},"1733":{"children":{}},"1734":{"children":{}},"1735":{"children":{}},"1736":{"children":{}},"1737":{"children":{}},"1738":{"children":{}},"1739":{"children":{}},"1740":{"children":{}},"1741":{"children":{}},"1742":{"children":{}},"1743":{"children":{}},"1744":{"children":{}},"1745":{"children":{}},"1746":{"children":{}},"1747":{"children":{}},"1748":{"children":{}},"1749":{"children":{}},"1750":{"children":{}},"1751":{"children":{}},"1752":{"children":{}},"1753":{"children":{}},"1754":{"children":{}},"1755":{"children":{}},"1756":{"children":{}},"1757":{"children":{}},"1758":{"children":{}},"1759":{"children":{}},"1760":{"children":{}},"1761":{"children":{}},"1762":{"children":{}},"1763":{"children":{}},"1764":{"children":{}},"1765":{"children":{}},"1766":{"children":{}},"1767":{"children":{}},"1768":{"children":{}},"1769":{"children":{}},"1770":{"children":{}},"1771":{"children":{}},"1772":{"children":{}},"1773":{"children":{}},"1774":{"children":{}},"1775":{"children":{}},"1776":{"children":{}},"1777":{"children":{}},"1778":{"children":{}},"1779":{"children":{}},"1780":{"children":{}},"1781":{"children":{}},"1782":{"children":{}},"1783":{"children":{}},"1784":{"children":{}},"1785":{"children":{}},"1786":{"children":{}},"1787":{"children":{}},"1788":{"children":{}},"1789":{"children":{}},"1790":{"children":{}},"1791":{"children":{}},"1792":{"children":{}},"1793":{"children":{}},"1794":{"children":{}},"1795":{"children":{}},"1796":{"children":{}},"1797":{"children":{}},"1798":{"children":{}},"1799":{"children":{}},"1800":{"children":{}},"1801":{"children":{}},"1802":{"children":{}},"1803":{"children":{}}}},"695":{"children":{"696":{"children":{}},"701":{"children":{}},"705":{"children":{}},"708":{"children":{}},"715":{"children":{}},"718":{"children":{}}}},"722":{"children":{"723":{"children":{}},"726":{"children":{}},"730":{"children":{}},"734":{"children":{}}}},"738":{"children":{"739":{"children":{}},"742":{"children":{}},"745":{"children":{}},"750":{"children":{}},"753":{"children":{}},"757":{"children":{}},"761":{"children":{}},"766":{"children":{}},"770":{"children":{}},"773":{"children":{}},"778":{"children":{}},"781":{"children":{}}}},"784":{"children":{"785":{"children":{}},"794":{"children":{}},"797":{"children":{}},"808":{"children":{}},"812":{"children":{}},"817":{"children":{}},"820":{"children":{}}}},"824":{"children":{"825":{"children":{}},"829":{"children":{}}}},"832":{"children":{"833":{"children":{}},"836":{"children":{}},"839":{"children":{}},"842":{"children":{}},"845":{"children":{}},"848":{"children":{}},"851":{"children":{}},"854":{"children":{}},"858":{"children":{}},"861":{"children":{}},"865":{"children":{}},"870":{"children":{}},"876":{"children":{}},"879":{"children":{}}}},"882":{"children":{"883":{"children":{}},"886":{"children":{}}}},"891":{"children":{"892":{"children":{}},"895":{"children":{}},"898":{"children":{}},"901":{"children":{}},"904":{"children":{}},"907":{"children":{}},"910":{"children":{}},"914":{"children":{}},"917":{"children":{}},"921":{"children":{}},"925":{"children":{}}}},"928":{"children":{"929":{"children":{}},"932":{"children":{}},"935":{"children":{}},"938":{"children":{}},"941":{"children":{}},"944":{"children":{}},"947":{"children":{}},"950":{"children":{}},"953":{"children":{}},"956":{"children":{}},"959":{"children":{}},"962":{"children":{}}}},"965":{"children":{"1804":{"children":{"1806":{"children":{}},"1818":{"children":{}},"1822":{"children":{}},"1827":{"children":{}},"1831":{"children":{}},"1835":{"children":{}},"1841":{"children":{}},"1845":{"children":{}}}},"1849":{"children":{"1851":{"children":{}},"1857":{"children":{}},"1863":{"children":{}},"1869":{"children":{}},"1874":{"children":{}},"1877":{"children":{}}}},"1878":{"children":{}},"1879":{"children":{"1881":{"children":{}},"1886":{"children":{}},"1891":{"children":{}},"1896":{"children":{}},"1901":{"children":{}},"1906":{"children":{}},"1911":{"children":{}},"1916":{"children":{}},"1921":{"children":{}}}},"1926":{"children":{"1928":{"children":{}},"1931":{"children":{}},"1934":{"children":{}},"1937":{"children":{}},"1940":{"children":{}},"1943":{"children":{}},"1946":{"children":{}},"1949":{"children":{}},"1953":{"children":{}},"1957":{"children":{}},"1962":{"children":{}},"1965":{"children":{}},"1969":{"children":{}},"1973":{"children":{}},"1977":{"children":{}},"1982":{"children":{}}}},"1988":{"children":{"1990":{"children":{"1992":{"children":{}},"1993":{"children":{}},"1994":{"children":{}},"1995":{"children":{}},"1996":{"children":{}},"1997":{"children":{}},"1998":{"children":{}},"1999":{"children":{}},"2000":{"children":{}},"2001":{"children":{}},"2002":{"children":{}},"2003":{"children":{}},"2004":{"children":{}},"2005":{"children":{}},"2006":{"children":{}},"2007":{"children":{}},"2008":{"children":{}},"2009":{"children":{}},"2010":{"children":{}},"2011":{"children":{}},"2012":{"children":{}},"2013":{"children":{}},"2014":{"children":{}},"2015":{"children":{}}}},"2016":{"children":{}}}},"2020":{"children":{"2021":{"children":{}},"2024":{"children":{}},"2025":{"children":{}},"2026":{"children":{}},"2027":{"children":{}},"2030":{"children":{}},"2032":{"children":{}},"2034":{"children":{}},"2038":{"children":{}},"2042":{"children":{}},"2046":{"children":{}},"2051":{"children":{}},"2059":{"children":{}},"2067":{"children":{}}}},"2071":{"children":{}},"2080":{"children":{}},"2091":{"children":{}},"2094":{"children":{}},"2097":{"children":{}},"2101":{"children":{}},"2104":{"children":{}},"2109":{"children":{}},"2117":{"children":{}},"2120":{"children":{}},"2123":{"children":{}},"2132":{"children":{}},"2137":{"children":{}},"2142":{"children":{}},"2146":{"children":{}},"2151":{"children":{}},"2153":{"children":{}},"2154":{"children":{"2155":{"children":{}},"2156":{"children":{}},"2157":{"children":{}},"2158":{"children":{}},"2159":{"children":{}},"2160":{"children":{}},"2161":{"children":{}},"2162":{"children":{}},"2163":{"children":{}},"2164":{"children":{}},"2165":{"children":{}},"2166":{"children":{}},"2167":{"children":{}},"2168":{"children":{}},"2169":{"children":{}},"2170":{"children":{}}}},"2171":{"children":{"2172":{"children":{}},"2173":{"children":{}},"2174":{"children":{}},"2175":{"children":{}}}},"2176":{"children":{}},"2177":{"children":{}},"2179":{"children":{}},"2182":{"children":{}},"2184":{"children":{}},"2186":{"children":{}},"2188":{"children":{}},"2190":{"children":{}},"2192":{"children":{}},"2194":{"children":{}},"2196":{"children":{}},"2199":{"children":{}},"2202":{"children":{}},"2206":{"children":{}},"2208":{"children":{}},"2211":{"children":{}},"2215":{"children":{}},"2218":{"children":{}},"2221":{"children":{}},"2226":{"children":{}},"2230":{"children":{"2232":{"children":{}},"2233":{"children":{}},"2234":{"children":{}},"2235":{"children":{}},"2236":{"children":{}},"2237":{"children":{}},"2238":{"children":{}},"2239":{"children":{}},"2240":{"children":{}},"2241":{"children":{}},"2242":{"children":{}},"2243":{"children":{}},"2244":{"children":{}},"2245":{"children":{}},"2246":{"children":{}},"2247":{"children":{}},"2248":{"children":{}},"2249":{"children":{}},"2250":{"children":{}},"2251":{"children":{}},"2252":{"children":{}},"2253":{"children":{}},"2254":{"children":{}},"2255":{"children":{}}}},"2256":{"children":{}},"2260":{"children":{}},"2267":{"children":{}},"2270":{"children":{}},"2273":{"children":{}},"2276":{"children":{}},"2279":{"children":{}},"2282":{"children":{}},"2285":{"children":{}},"2288":{"children":{}},"2295":{"children":{}},"2298":{"children":{}},"2302":{"children":{}},"2310":{"children":{}},"2318":{"children":{}},"2322":{"children":{}},"2331":{"children":{}},"2335":{"children":{}},"2339":{"children":{}},"2343":{"children":{}},"2347":{"children":{}},"2351":{"children":{}},"2354":{"children":{}},"2359":{"children":{}}}},"966":{"children":{"967":{"children":{}},"969":{"children":{}}}},"972":{"children":{"973":{"children":{}},"976":{"children":{}},"983":{"children":{}}}},"986":{"children":{"987":{"children":{}},"989":{"children":{}},"993":{"children":{}}}},"997":{"children":{"998":{"children":{}},"1000":{"children":{}},"1004":{"children":{}},"1008":{"children":{}},"1012":{"children":{}},"1016":{"children":{}},"1020":{"children":{}},"1024":{"children":{}},"1027":{"children":{}},"1030":{"children":{}},"1035":{"children":{}},"1038":{"children":{}},"1044":{"children":{}},"1046":{"children":{}},"1052":{"children":{}},"1055":{"children":{}},"1059":{"children":{}},"1062":{"children":{}},"1066":{"children":{}}}},"1072":{"children":{"1073":{"children":{}},"1076":{"children":{}},"1079":{"children":{}},"1084":{"children":{}},"1089":{"children":{}}}},"1092":{"children":{"1093":{"children":{}},"1097":{"children":{}},"1104":{"children":{}},"1111":{"children":{}},"1115":{"children":{}}}},"1118":{"children":{"1119":{"children":{}},"1121":{"children":{}},"1126":{"children":{}},"1131":{"children":{}},"1136":{"children":{}},"1141":{"children":{}},"1144":{"children":{}}}},"1149":{"children":{"1150":{"children":{}},"1153":{"children":{}},"1156":{"children":{}},"1158":{"children":{}},"1165":{"children":{}}}},"1169":{"children":{"2363":{"children":{}},"2364":{"children":{}},"2365":{"children":{}},"2366":{"children":{}},"2367":{"children":{}},"2368":{"children":{}},"2369":{"children":{}},"2370":{"children":{}},"2371":{"children":{}},"2372":{"children":{}},"2373":{"children":{}},"2374":{"children":{}},"2375":{"children":{}},"2376":{"children":{}},"2377":{"children":{}},"2378":{"children":{}},"2379":{"children":{}},"2380":{"children":{}},"2381":{"children":{}},"2382":{"children":{}},"2383":{"children":{}},"2384":{"children":{}},"2385":{"children":{}},"2386":{"children":{}},"2387":{"children":{}},"2388":{"children":{}},"2389":{"children":{}},"2390":{"children":{}},"2391":{"children":{}},"2392":{"children":{}},"2393":{"children":{}},"2394":{"children":{}},"2395":{"children":{}},"2396":{"children":{}},"2397":{"children":{}},"2398":{"children":{}},"2399":{"children":{}},"2400":{"children":{}},"2401":{"children":{}},"2402":{"children":{}},"2403":{"children":{}},"2404":{"children":{}},"2405":{"children":{}},"2406":{"children":{}},"2407":{"children":{}},"2408":{"children":{}},"2409":{"children":{}},"2410":{"children":{}},"2411":{"children":{}},"2412":{"children":{}},"2413":{"children":{}},"2414":{"children":{}},"2415":{"children":{}},"2416":{"children":{}},"2417":{"children":{}},"2418":{"children":{}},"2419":{"children":{}},"2420":{"children":{}},"2421":{"children":{}},"2422":{"children":{}},"2423":{"children":{}},"2424":{"children":{}},"2425":{"children":{}},"2426":{"children":{}},"2427":{"children":{}},"2428":{"children":{}},"2429":{"children":{}},"2430":{"children":{}},"2431":{"children":{}},"2432":{"children":{}},"2433":{"children":{}},"2434":{"children":{}},"2435":{"children":{}},"2436":{"children":{}},"2437":{"children":{}},"2438":{"children":{}},"2439":{"children":{}},"2440":{"children":{}},"2441":{"children":{}},"2442":{"children":{}},"2443":{"children":{}},"2444":{"children":{}},"2445":{"children":{}},"2446":{"children":{}},"2447":{"children":{}},"2448":{"children":{}},"2449":{"children":{}},"2450":{"children":{}},"2451":{"children":{}},"2452":{"children":{}},"2453":{"children":{}},"2454":{"children":{}},"2455":{"children":{}},"2456":{"children":{}},"2457":{"children":{}},"2458":{"children":{}},"2459":{"children":{}},"2460":{"children":{}},"2461":{"children":{}},"2462":{"children":{}},"2463":{"children":{}},"2464":{"children":{}},"2465":{"children":{}},"2466":{"children":{}},"2467":{"children":{}},"2468":{"children":{}},"2469":{"children":{}},"2470":{"children":{}},"2471":{"children":{}},"2472":{"children":{}},"2473":{"children":{}},"2474":{"children":{}},"2475":{"children":{}},"2476":{"children":{}},"2477":{"children":{}},"2478":{"children":{}},"2479":{"children":{}},"2480":{"children":{}},"2481":{"children":{}},"2482":{"children":{}},"2483":{"children":{}}}},"1170":{"children":{"1171":{"children":{}}}},"1174":{"children":{"1175":{"children":{}},"1182":{"children":{}},"1189":{"children":{}}}},"1197":{"children":{"1198":{"children":{}},"1202":{"children":{}},"1207":{"children":{}},"1210":{"children":{}},"1213":{"children":{}},"1216":{"children":{}},"1219":{"children":{}}}},"1224":{"children":{"1225":{"children":{}},"1229":{"children":{}},"1232":{"children":{"1233":{"children":{}},"1234":{"children":{}},"1235":{"children":{}}}}}},"1236":{"children":{"1237":{"children":{}},"1239":{"children":{}},"1241":{"children":{}},"1249":{"children":{}},"1257":{"children":{}},"1265":{"children":{}},"1274":{"children":{}}}},"1277":{"children":{"1278":{"children":{}}}},"1281":{"children":{"1282":{"children":{}},"1291":{"children":{}},"1303":{"children":{}},"1309":{"children":{}},"1316":{"children":{}},"1323":{"children":{}}}},"1326":{"children":{"1327":{"children":{}},"1329":{"children":{}},"1331":{"children":{}},"1333":{"children":{}},"1335":{"children":{}},"1337":{"children":{}},"1339":{"children":{}},"1344":{"children":{}},"1346":{"children":{}}}},"1347":{"children":{"1348":{"children":{"1349":{"children":{}},"1350":{"children":{}}}}}},"1351":{"children":{"1352":{"children":{}},"1354":{"children":{}},"1356":{"children":{}},"1359":{"children":{}},"1361":{"children":{}},"1363":{"children":{}},"1367":{"children":{"1368":{"children":{}},"1369":{"children":{}},"1373":{"children":{}},"1377":{"children":{}}}},"1379":{"children":{}},"1381":{"children":{}}}},"1383":{"children":{"1384":{"children":{}},"1387":{"children":{}},"1390":{"children":{}},"1393":{"children":{}},"1395":{"children":{}},"1398":{"children":{}},"1401":{"children":{}},"1404":{"children":{}},"1407":{"children":{}},"1413":{"children":{}},"1415":{"children":{}},"1419":{"children":{}},"1422":{"children":{}},"1426":{"children":{}},"1429":{"children":{}},"1432":{"children":{}}}},"1435":{"children":{"1436":{"children":{}}}},"1454":{"children":{"1455":{"children":{}},"1458":{"children":{}},"1465":{"children":{}},"1471":{"children":{}},"1474":{"children":{}},"1477":{"children":{}}}},"1480":{"children":{"1481":{"children":{}},"1486":{"children":{}},"1495":{"children":{}},"1506":{"children":{"1507":{"children":{}},"1513":{"children":{}},"1514":{"children":{}},"1525":{"children":{}},"1536":{"children":{}},"1537":{"children":{}},"1540":{"children":{}},"1541":{"children":{}},"1543":{"children":{}},"1547":{"children":{}},"1551":{"children":{}},"1553":{"children":{}},"1556":{"children":{}}}}}},"1558":{"children":{"2484":{"children":{}},"2487":{"children":{}},"2490":{"children":{"2491":{"children":{}},"2492":{"children":{}},"2496":{"children":{}}}},"2499":{"children":{}},"2500":{"children":{}},"2501":{"children":{}},"2502":{"children":{}},"2503":{"children":{}},"2511":{"children":{}},"2515":{"children":{}},"2520":{"children":{}},"2522":{"children":{}},"2527":{"children":{}},"2530":{"children":{}},"2533":{"children":{}},"2537":{"children":{}},"2541":{"children":{}},"2544":{"children":{}},"2547":{"children":{}},"2550":{"children":{}},"2554":{"children":{}},"2557":{"children":{}},"2561":{"children":{}},"2566":{"children":{}},"2572":{"children":{}},"2580":{"children":{}},"2586":{"children":{}},"2591":{"children":{}},"2595":{"children":{}},"2603":{"children":{}},"2606":{"children":{"2607":{"children":{}},"2611":{"children":{}},"2612":{"children":{}},"2613":{"children":{}},"2615":{"children":{}},"2617":{"children":{}},"2620":{"children":{}},"2623":{"children":{}},"2626":{"children":{}}}},"2629":{"children":{}},"2635":{"children":{}},"2638":{"children":{}},"2643":{"children":{"2644":{"children":{}},"2645":{"children":{}}}},"2646":{"children":{}},"2647":{"children":{"2649":{"children":{}},"2650":{"children":{}}}},"2651":{"children":{}}}},"1559":{"children":{"2655":{"children":{}},"2658":{"children":{"2659":{"children":{}},"2660":{"children":{}}}},"2661":{"children":{}},"2664":{"children":{"2665":{"children":{}},"2666":{"children":{}}}},"2667":{"children":{}},"2670":{"children":{"2671":{"children":{}},"2672":{"children":{}},"2673":{"children":{}}}},"2674":{"children":{}},"2677":{"children":{"2678":{"children":{}},"2679":{"children":{}}}},"2680":{"children":{}},"2683":{"children":{}},"2684":{"children":{}},"2687":{"children":{}},"2690":{"children":{}},"2691":{"children":{}},"2694":{"children":{}},"2695":{"children":{"2696":{"children":{}},"2697":{"children":{}}}},"2698":{"children":{"2699":{"children":{}},"2700":{"children":{}}}},"2701":{"children":{}},"2704":{"children":{"2705":{"children":{}},"2706":{"children":{}},"2707":{"children":{}}}},"2708":{"children":{"2709":{"children":{}},"2710":{"children":{}}}},"2711":{"children":{}},"2714":{"children":{}},"2717":{"children":{}},"2719":{"children":{"2720":{"children":{}}}},"2721":{"children":{}},"2732":{"children":{}},"2736":{"children":{}}}},"1560":{"children":{"1561":{"children":{}},"1568":{"children":{}},"1574":{"children":{}},"1578":{"children":{}},"1582":{"children":{}},"1587":{"children":{}},"1592":{"children":{"1593":{"children":{}},"1594":{"children":{}},"1595":{"children":{}}}},"1596":{"children":{"1597":{"children":{}}}},"1598":{"children":{"1600":{"children":{}},"1608":{"children":{}},"1615":{"children":{}},"1620":{"children":{}},"1625":{"children":{}},"1631":{"children":{}}}}}},"project":{"children":{}}}
