{"id":278,"name":"initializeArrayWithValues","kind":64,"kindString":"Function","flags":{},"children":[],"sources":[{"fileName":"utils/src/array.ts","fullFileName":"/home/runner/work/fe-tools/fe-tools/utils/packages/utils/src/array.ts","line":456,"character":16,"url":"https://github.com/MichealWayne/fe-tools/blob/cc3303f/utils/packages/utils/src/array.ts#L456"}],"signatures":[{"id":279,"name":"initializeArrayWithValues","kind":4096,"kindString":"Call signature","flags":{},"comment":{"summary":[],"blockTags":[{"tag":"@function","content":[{"kind":"text","text":"initializeArrayWithValues"}]},{"tag":"@description","content":[{"kind":"text","text":"初始化数组"}]},{"tag":"@returns","content":[{"kind":"text","text":"初始化后的数组"}]},{"tag":"@example","content":[{"kind":"code","text":"```ts\ninitializeArrayWithValues(5, 2);  // [2,2,2,2,2]\r\ninitializeArrayWithValues(5);  // [0,0,0,0,0]\n```"}]}]},"parameters":[{"id":280,"name":"len","kind":32768,"kindString":"Parameter","flags":{},"comment":{"summary":[{"kind":"text","text":"长度"}]},"type":{"type":"intrinsic","name":"number"},"text":{"comment":"<p>长度</p>\n"}},{"id":281,"name":"value","kind":32768,"kindString":"Parameter","flags":{},"comment":{"summary":[{"kind":"text","text":"值"}]},"type":{"type":"intrinsic","name":"number"},"defaultValue":"0","text":{"comment":"<p>值</p>\n"}}],"type":{"type":"array","elementType":{"type":"intrinsic","name":"any"}},"is":{"declaration":false},"location":{"query":"Array.Function.initializeArrayWithValues","hash":"initializeArrayWithValues"},"text":{"comment":"<h5>Function:</h5><p>initializeArrayWithValues</p>\n<h5>Description:</h5><p>初始化数组</p>\n<h5>Returns:</h5><p>初始化后的数组</p>\n<h5>Example:</h5><pre><code class=\"language-ts\"><span class=\"pl-en\">initializeArrayWithValues</span>(<span class=\"pl-c1\">5</span>, <span class=\"pl-c1\">2</span>);  <span class=\"pl-c\">// [2,2,2,2,2]</span>\n<span class=\"pl-en\">initializeArrayWithValues</span>(<span class=\"pl-c1\">5</span>);  <span class=\"pl-c\">// [0,0,0,0,0]</span>\n</code></pre>\n"},"sources":[{"fileName":"utils/src/array.ts","fullFileName":"/home/runner/work/fe-tools/fe-tools/utils/packages/utils/src/array.ts","line":456,"character":0,"url":"https://github.com/MichealWayne/fe-tools/blob/cc3303f/utils/packages/utils/src/array.ts#L456"}],"parentId":278}],"is":{"declaration":true},"location":{"query":"Array.Function.initializeArrayWithValues","hash":""},"text":{},"parentId":154}
