{"id":890,"name":"getKeyName","kind":64,"kindString":"Function","flags":{},"children":[],"sources":[{"fileName":"packages/web-utils/src/keyboard.ts","fullFileName":"/home/runner/work/fe-tools/fe-tools/utils/packages/web-utils/src/keyboard.ts","line":124,"character":16,"url":"https://github.com/MichealWayne/fe-tools/blob/9ff97b7/utils/packages/web-utils/src/keyboard.ts#L124"}],"signatures":[{"id":891,"name":"getKeyName","kind":4096,"kindString":"Call signature","flags":{},"comment":{"summary":[],"blockTags":[{"tag":"@function","content":[{"kind":"text","text":"getKeyName"}]},{"tag":"@description","content":[{"kind":"text","text":"通过将键码转换为更易于理解的键名"}]},{"tag":"@returns","content":[{"kind":"text","text":"键名"}]},{"tag":"@example","content":[{"kind":"code","text":"```ts\ngetKeyName(13); // 'Enter'\n```"}]}]},"parameters":[{"id":892,"name":"keycode","kind":32768,"kindString":"Parameter","flags":{},"comment":{"summary":[{"kind":"text","text":"键码"}]},"type":{"type":"union","types":[{"type":"literal","value":122},{"type":"literal","value":65},{"type":"literal","value":9},{"type":"literal","value":8},{"type":"literal","value":100},{"type":"literal","value":18},{"type":"literal","value":17},{"type":"literal","value":13},{"type":"literal","value":32},{"type":"literal","value":33},{"type":"literal","value":34},{"type":"literal","value":35},{"type":"literal","value":36},{"type":"literal","value":37},{"type":"literal","value":42},{"type":"literal","value":45},{"type":"literal","value":46},{"type":"literal","value":50},{"type":"literal","value":51},{"type":"literal","value":52},{"type":"literal","value":53},{"type":"literal","value":54},{"type":"literal","value":71},{"type":"literal","value":81},{"type":"literal","value":82},{"type":"literal","value":91},{"type":"literal","value":16},{"type":"literal","value":19},{"type":"literal","value":20},{"type":"literal","value":27},{"type":"literal","value":38},{"type":"literal","value":39},{"type":"literal","value":40},{"type":"literal","value":48},{"type":"literal","value":49},{"type":"literal","value":55},{"type":"literal","value":56},{"type":"literal","value":57},{"type":"literal","value":66},{"type":"literal","value":67},{"type":"literal","value":68},{"type":"literal","value":69},{"type":"literal","value":70},{"type":"literal","value":72},{"type":"literal","value":73},{"type":"literal","value":74},{"type":"literal","value":75},{"type":"literal","value":76},{"type":"literal","value":77},{"type":"literal","value":78},{"type":"literal","value":79},{"type":"literal","value":80},{"type":"literal","value":83},{"type":"literal","value":84},{"type":"literal","value":85},{"type":"literal","value":86},{"type":"literal","value":87},{"type":"literal","value":88},{"type":"literal","value":89},{"type":"literal","value":90},{"type":"literal","value":93},{"type":"literal","value":96},{"type":"literal","value":97},{"type":"literal","value":98},{"type":"literal","value":99},{"type":"literal","value":101},{"type":"literal","value":102},{"type":"literal","value":103},{"type":"literal","value":104},{"type":"literal","value":105},{"type":"literal","value":106},{"type":"literal","value":107},{"type":"literal","value":109},{"type":"literal","value":110},{"type":"literal","value":111},{"type":"literal","value":112},{"type":"literal","value":113},{"type":"literal","value":114},{"type":"literal","value":115},{"type":"literal","value":116},{"type":"literal","value":117},{"type":"literal","value":118},{"type":"literal","value":119},{"type":"literal","value":120},{"type":"literal","value":121},{"type":"literal","value":123},{"type":"literal","value":144},{"type":"literal","value":145},{"type":"literal","value":182},{"type":"literal","value":183},{"type":"literal","value":186},{"type":"literal","value":187},{"type":"literal","value":188},{"type":"literal","value":189},{"type":"literal","value":190},{"type":"literal","value":191},{"type":"literal","value":192},{"type":"literal","value":219},{"type":"literal","value":220},{"type":"literal","value":221},{"type":"literal","value":222}]},"text":{"comment":"<p>键码</p>\n"}}],"type":{"type":"intrinsic","name":"string"},"is":{"declaration":false},"location":{"query":"keyboard.Function.getKeyName","hash":"getKeyName"},"text":{"comment":"<h5>Function:</h5><p>getKeyName</p>\n<h5>Description:</h5><p>通过将键码转换为更易于理解的键名</p>\n<h5>Returns:</h5><p>键名</p>\n<h5>Example:</h5><pre><code class=\"language-ts\"><span class=\"pl-en\">getKeyName</span>(<span class=\"pl-c1\">13</span>); <span class=\"pl-c\">// 'Enter'</span>\n</code></pre>\n"},"sources":[{"fileName":"packages/web-utils/src/keyboard.ts","fullFileName":"/home/runner/work/fe-tools/fe-tools/utils/packages/web-utils/src/keyboard.ts","line":124,"character":0,"url":"https://github.com/MichealWayne/fe-tools/blob/9ff97b7/utils/packages/web-utils/src/keyboard.ts#L124"}],"parentId":890}],"is":{"declaration":true},"location":{"query":"keyboard.Function.getKeyName","hash":""},"text":{},"parentId":889}
