{"id":1144,"name":"getMobileOS","kind":64,"kindString":"Function","flags":{},"children":[],"sources":[{"fileName":"web-utils/src/platform.ts","fullFileName":"/home/runner/work/fe-tools/fe-tools/utils/packages/web-utils/src/platform.ts","line":124,"character":16,"url":"https://github.com/MichealWayne/fe-tools/blob/3d8c932/utils/packages/web-utils/src/platform.ts#L124"}],"signatures":[{"id":1145,"name":"getMobileOS","kind":4096,"kindString":"Call signature","flags":{},"comment":{"summary":[],"blockTags":[{"tag":"@function","content":[{"kind":"text","text":"getMobileOS"}]},{"tag":"@description","content":[{"kind":"text","text":"获取当前页面所处的移动设备系统"}]},{"tag":"@returns","content":[{"kind":"text","text":"移动设备系统，如：{'android': 0, 'ios': 11.2}"}]}]},"type":{"type":"reflection","declaration":{"id":1146,"name":"getMobileOS","kind":65536,"kindString":"Type literal","flags":{},"children":[{"id":1147,"name":"android","kind":1024,"kindString":"Property","flags":{},"sources":[{"fileName":"web-utils/src/platform.ts","fullFileName":"/home/runner/work/fe-tools/fe-tools/utils/packages/web-utils/src/platform.ts","line":126,"character":4,"url":"https://github.com/MichealWayne/fe-tools/blob/3d8c932/utils/packages/web-utils/src/platform.ts#L126"}],"type":{"type":"intrinsic","name":"number"},"defaultValue":"0","is":{"declaration":true},"location":{"query":"Platform.Function.getMobileOS","hash":"getMobileOS.android"},"text":{},"parentId":1144},{"id":1148,"name":"ios","kind":1024,"kindString":"Property","flags":{},"sources":[{"fileName":"web-utils/src/platform.ts","fullFileName":"/home/runner/work/fe-tools/fe-tools/utils/packages/web-utils/src/platform.ts","line":127,"character":4,"url":"https://github.com/MichealWayne/fe-tools/blob/3d8c932/utils/packages/web-utils/src/platform.ts#L127"}],"type":{"type":"intrinsic","name":"number"},"defaultValue":"0","is":{"declaration":true},"location":{"query":"Platform.Function.getMobileOS","hash":"getMobileOS.ios"},"text":{},"parentId":1144}],"groups":[{"title":"Properties","children":[1147,1148]}],"sources":[{"fileName":"web-utils/src/platform.ts","line":125,"character":13,"url":"https://github.com/MichealWayne/fe-tools/blob/3d8c932/utils/packages/web-utils/src/platform.ts#L125"}],"location":{"query":"Platform.Function.getMobileOS","hash":"getMobileOS"}}},"is":{"declaration":false},"location":{"query":"Platform.Function.getMobileOS","hash":"getMobileOS"},"text":{"comment":"<h5>Function:</h5><p>getMobileOS</p>\n<h5>Description:</h5><p>获取当前页面所处的移动设备系统</p>\n<h5>Returns:</h5><p>移动设备系统，如：{&#39;android&#39;: 0, &#39;ios&#39;: 11.2}</p>\n"},"sources":[{"fileName":"web-utils/src/platform.ts","fullFileName":"/home/runner/work/fe-tools/fe-tools/utils/packages/web-utils/src/platform.ts","line":124,"character":0,"url":"https://github.com/MichealWayne/fe-tools/blob/3d8c932/utils/packages/web-utils/src/platform.ts#L124"}],"parentId":1144}],"is":{"declaration":true},"location":{"query":"Platform.Function.getMobileOS","hash":""},"text":{},"parentId":1135}
