{"id":632,"name":"decapitalize","kind":64,"kindString":"Function","flags":{},"children":[],"sources":[{"fileName":"utils/src/string.ts","fullFileName":"/home/runner/work/fe-tools/fe-tools/utils/packages/utils/src/string.ts","line":56,"character":16,"url":"https://github.com/MichealWayne/fe-tools/blob/6f6235b/utils/packages/utils/src/string.ts#L56"}],"signatures":[{"id":633,"name":"decapitalize","kind":4096,"kindString":"Call signature","flags":{},"comment":{"summary":[],"blockTags":[{"tag":"@function","content":[{"kind":"text","text":"decapitalize"}]},{"tag":"@description","content":[{"kind":"text","text":"用于将字符串的第一个字母转换为小写字母"}]},{"tag":"@returns","content":[]},{"tag":"@example","content":[{"kind":"code","text":"```ts\ndecapitalize('Hello'); // 'hello'\r\ndecapitalize('World'); // 'world'\n```"}]}]},"parameters":[{"id":634,"name":"paramString","kind":32768,"kindString":"Parameter","flags":{},"originalName":"__namedParameters","type":{"type":"intrinsic","name":"string"},"text":{}}],"type":{"type":"intrinsic","name":"string"},"is":{"declaration":false},"location":{"query":"String.Function.decapitalize","hash":"decapitalize"},"text":{"comment":"<h5>Function:</h5><p>decapitalize</p>\n<h5>Description:</h5><p>用于将字符串的第一个字母转换为小写字母</p>\n<h5>Returns:</h5><h5>Example:</h5><pre><code class=\"language-ts\"><span class=\"pl-en\">decapitalize</span>(<span class=\"pl-s\"><span class=\"pl-pds\">'</span>Hello<span class=\"pl-pds\">'</span></span>); <span class=\"pl-c\">// 'hello'</span>\n<span class=\"pl-en\">decapitalize</span>(<span class=\"pl-s\"><span class=\"pl-pds\">'</span>World<span class=\"pl-pds\">'</span></span>); <span class=\"pl-c\">// 'world'</span>\n</code></pre>\n"},"sources":[{"fileName":"utils/src/string.ts","fullFileName":"/home/runner/work/fe-tools/fe-tools/utils/packages/utils/src/string.ts","line":56,"character":0,"url":"https://github.com/MichealWayne/fe-tools/blob/6f6235b/utils/packages/utils/src/string.ts#L56"}],"parentId":632}],"is":{"declaration":true},"location":{"query":"String.Function.decapitalize","hash":""},"text":{},"parentId":622}
