{"id":875,"name":"isBase64","kind":64,"kindString":"Function","flags":{},"children":[],"sources":[{"fileName":"packages/utils/src/validators.ts","fullFileName":"/home/runner/work/fe-tools/fe-tools/utils/packages/utils/src/validators.ts","line":205,"character":16,"url":"https://github.com/MichealWayne/fe-tools/blob/88d7404/utils/packages/utils/src/validators.ts#L205"}],"signatures":[{"id":876,"name":"isBase64","kind":4096,"kindString":"Call signature","flags":{},"comment":{"summary":[],"blockTags":[{"tag":"@function","content":[{"kind":"text","text":"isBase64"}]},{"tag":"@description","content":[{"kind":"text","text":"检查字符串是否为有效的Base64编码。Checks if string is valid Base64 encoding"}]},{"tag":"@returns","content":[{"kind":"text","text":"如果是有效Base64则返回true。True if valid Base64"}]},{"tag":"@example","content":[{"kind":"code","text":"```ts\nisBase64('SGVsbG8gV29ybGQ='); // -> true\nisBase64('not base64'); // -> false\n```"}]}]},"parameters":[{"id":877,"name":"str","kind":32768,"kindString":"Parameter","flags":{},"comment":{"summary":[{"kind":"text","text":"要验证的字符串。String to validate"}]},"type":{"type":"intrinsic","name":"string"},"text":{"comment":"<p>要验证的字符串。String to validate</p>\n"}}],"type":{"type":"intrinsic","name":"boolean"},"is":{"declaration":false},"location":{"query":"Validators.Function.isBase64","hash":"isBase64"},"text":{"comment":"<h5>Function:</h5><p>isBase64</p>\n<h5>Description:</h5><p>检查字符串是否为有效的Base64编码。Checks if string is valid Base64 encoding</p>\n<h5>Returns:</h5><p>如果是有效Base64则返回true。True if valid Base64</p>\n<h5>Example:</h5><pre><code class=\"language-ts\"><span class=\"pl-en\">isBase64</span>(<span class=\"pl-s\"><span class=\"pl-pds\">'</span>SGVsbG8gV29ybGQ=<span class=\"pl-pds\">'</span></span>); <span class=\"pl-c\">// -> true</span>\n<span class=\"pl-en\">isBase64</span>(<span class=\"pl-s\"><span class=\"pl-pds\">'</span>not base64<span class=\"pl-pds\">'</span></span>); <span class=\"pl-c\">// -> false</span>\n</code></pre>\n"},"sources":[{"fileName":"packages/utils/src/validators.ts","fullFileName":"/home/runner/work/fe-tools/fe-tools/utils/packages/utils/src/validators.ts","line":205,"character":0,"url":"https://github.com/MichealWayne/fe-tools/blob/88d7404/utils/packages/utils/src/validators.ts#L205"}],"parentId":875}],"is":{"declaration":true},"location":{"query":"Validators.Function.isBase64","hash":""},"text":{},"parentId":841}
