{"id":1244,"name":"canvas-utils/src","kind":2,"kindString":"Module","flags":{},"children":[],"groups":[{"title":"Interfaces","children":[1858]},{"title":"Type Aliases","children":[1862,1861,1866]},{"title":"Variables","children":[1734,1737,1735,1736]},{"title":"Functions","children":[1755,1855,1821,1757,1746,1830,1801,1796,1807,1815,1738,1765,1782,1785,1838,1792,1762,1768,1772,1789,1779,1776,1841,1826,1847,1850,1750]}],"sources":[{"fileName":"canvas-utils/src/index.ts","fullFileName":"/home/runner/work/fe-tools/fe-tools/utils/packages/canvas-utils/src/index.ts","line":7,"character":0,"url":"https://github.com/MichealWayne/fe-tools/blob/c7fbca0/utils/packages/canvas-utils/src/index.ts#L7"}],"is":{"declaration":true},"location":{"query":"Module.canvas-utils/src","hash":""},"text":{}}
