{"id":1407,"name":"WorkerPool","kind":128,"kindString":"Class","flags":{},"comment":{"summary":[{"kind":"text","text":"工作线程池 - 管理多个 Worker 实例"}]},"children":[{"id":1408,"name":"constructor","kind":512,"kindString":"Constructor","flags":{},"sources":[{"fileName":"packages/web-utils/src/worker.ts","fullFileName":"/home/runner/work/fe-tools/fe-tools/utils/packages/web-utils/src/worker.ts","line":44,"character":2,"url":"https://github.com/MichealWayne/fe-tools/blob/88d7404/utils/packages/web-utils/src/worker.ts#L44"}],"signatures":[{"id":1409,"name":"constructor","kind":16384,"kindString":"Constructor signature","flags":{},"comment":{"summary":[{"kind":"text","text":"创建工作线程池"}]},"parameters":[{"id":1410,"name":"workerScript","kind":32768,"kindString":"Parameter","flags":{},"comment":{"summary":[{"kind":"text","text":"Worker 脚本路径或函数"}]},"type":{"type":"union","types":[{"type":"intrinsic","name":"string"},{"type":"reflection","declaration":{"id":1411,"name":"__type","kind":65536,"kindString":"Type literal","flags":{},"sources":[{"fileName":"packages/web-utils/src/worker.ts","line":45,"character":36,"url":"https://github.com/MichealWayne/fe-tools/blob/88d7404/utils/packages/web-utils/src/worker.ts#L45"}],"signatures":[{"id":1412,"name":"__type","kind":4096,"kindString":"Call signature","flags":{},"type":{"type":"intrinsic","name":"any"}}]}}]},"text":{"comment":"<p>Worker 脚本路径或函数</p>\n"}},{"id":1413,"name":"size","kind":32768,"kindString":"Parameter","flags":{},"comment":{"summary":[{"kind":"text","text":"线程池大小"}]},"type":{"type":"intrinsic","name":"number"},"defaultValue":"...","text":{"comment":"<p>线程池大小</p>\n"}}],"type":{"type":"reference","id":1407,"name":"WorkerPool"},"is":{"declaration":false},"location":{"query":"web-utils/src/worker.WorkerPool.Constructor.constructor","hash":"constructor.new WorkerPool"},"text":{"comment":"<p>创建工作线程池</p>\n"},"sources":[{"fileName":"packages/web-utils/src/worker.ts","fullFileName":"/home/runner/work/fe-tools/fe-tools/utils/packages/web-utils/src/worker.ts","line":44,"character":2,"url":"https://github.com/MichealWayne/fe-tools/blob/88d7404/utils/packages/web-utils/src/worker.ts#L44"}],"parentId":1408}],"is":{"declaration":true},"location":{"query":"web-utils/src/worker.Class.WorkerPool","hash":"constructor"},"text":{},"parentId":1407},{"id":1426,"name":"activeWorkers","kind":1024,"kindString":"Property","flags":{"isPrivate":true},"sources":[{"fileName":"packages/web-utils/src/worker.ts","fullFileName":"/home/runner/work/fe-tools/fe-tools/utils/packages/web-utils/src/worker.ts","line":37,"character":10,"url":"https://github.com/MichealWayne/fe-tools/blob/88d7404/utils/packages/web-utils/src/worker.ts#L37"}],"type":{"type":"reference","typeArguments":[{"type":"reference","name":"Worker","qualifiedName":"Worker","package":"typescript"}],"name":"Set","qualifiedName":"Set","package":"typescript"},"defaultValue":"...","is":{"declaration":true},"location":{"query":"web-utils/src/worker.Class.WorkerPool","hash":"activeWorkers"},"text":{},"parentId":1407},{"id":1415,"name":"queue","kind":1024,"kindString":"Property","flags":{"isPrivate":true},"sources":[{"fileName":"packages/web-utils/src/worker.ts","fullFileName":"/home/runner/work/fe-tools/fe-tools/utils/packages/web-utils/src/worker.ts","line":32,"character":10,"url":"https://github.com/MichealWayne/fe-tools/blob/88d7404/utils/packages/web-utils/src/worker.ts#L32"}],"type":{"type":"array","elementType":{"type":"reflection","declaration":{"id":1416,"name":"__type","kind":65536,"kindString":"Type literal","flags":{},"children":[{"id":1422,"name":"reject","kind":1024,"kindString":"Property","flags":{},"sources":[{"fileName":"packages/web-utils/src/worker.ts","line":35,"character":4,"url":"https://github.com/MichealWayne/fe-tools/blob/88d7404/utils/packages/web-utils/src/worker.ts#L35"}],"type":{"type":"reflection","declaration":{"id":1423,"name":"__type","kind":65536,"kindString":"Type literal","flags":{},"sources":[{"fileName":"packages/web-utils/src/worker.ts","line":35,"character":12,"url":"https://github.com/MichealWayne/fe-tools/blob/88d7404/utils/packages/web-utils/src/worker.ts#L35"}],"signatures":[{"id":1424,"name":"__type","kind":4096,"kindString":"Call signature","flags":{},"parameters":[{"id":1425,"name":"reason","kind":32768,"kindString":"Parameter","flags":{"isOptional":true},"type":{"type":"intrinsic","name":"any"}}],"type":{"type":"intrinsic","name":"void"}}]}}},{"id":1418,"name":"resolve","kind":1024,"kindString":"Property","flags":{},"sources":[{"fileName":"packages/web-utils/src/worker.ts","line":34,"character":4,"url":"https://github.com/MichealWayne/fe-tools/blob/88d7404/utils/packages/web-utils/src/worker.ts#L34"}],"type":{"type":"reflection","declaration":{"id":1419,"name":"__type","kind":65536,"kindString":"Type literal","flags":{},"sources":[{"fileName":"packages/web-utils/src/worker.ts","line":34,"character":13,"url":"https://github.com/MichealWayne/fe-tools/blob/88d7404/utils/packages/web-utils/src/worker.ts#L34"}],"signatures":[{"id":1420,"name":"__type","kind":4096,"kindString":"Call signature","flags":{},"parameters":[{"id":1421,"name":"value","kind":32768,"kindString":"Parameter","flags":{},"type":{"type":"intrinsic","name":"any"}}],"type":{"type":"intrinsic","name":"void"}}]}}},{"id":1417,"name":"task","kind":1024,"kindString":"Property","flags":{},"sources":[{"fileName":"packages/web-utils/src/worker.ts","line":33,"character":4,"url":"https://github.com/MichealWayne/fe-tools/blob/88d7404/utils/packages/web-utils/src/worker.ts#L33"}],"type":{"type":"intrinsic","name":"any"}}],"groups":[{"title":"Properties","children":[1422,1418,1417]}],"sources":[{"fileName":"packages/web-utils/src/worker.ts","line":32,"character":23,"url":"https://github.com/MichealWayne/fe-tools/blob/88d7404/utils/packages/web-utils/src/worker.ts#L32"}]}}},"defaultValue":"[]","is":{"declaration":true},"location":{"query":"web-utils/src/worker.Class.WorkerPool","hash":"queue"},"text":{},"parentId":1407},{"id":1430,"name":"size","kind":1024,"kindString":"Property","flags":{"isPrivate":true},"comment":{"summary":[{"kind":"text","text":"线程池大小"}]},"sources":[{"fileName":"packages/web-utils/src/worker.ts","fullFileName":"/home/runner/work/fe-tools/fe-tools/utils/packages/web-utils/src/worker.ts","line":46,"character":12,"url":"https://github.com/MichealWayne/fe-tools/blob/88d7404/utils/packages/web-utils/src/worker.ts#L46"}],"type":{"type":"intrinsic","name":"number"},"defaultValue":"...","is":{"declaration":true},"location":{"query":"web-utils/src/worker.Class.WorkerPool","hash":"size"},"text":{"comment":"<p>线程池大小</p>\n"},"parentId":1407},{"id":1427,"name":"workerScript","kind":1024,"kindString":"Property","flags":{"isPrivate":true},"comment":{"summary":[{"kind":"text","text":"Worker 脚本路径或函数"}]},"sources":[{"fileName":"packages/web-utils/src/worker.ts","fullFileName":"/home/runner/work/fe-tools/fe-tools/utils/packages/web-utils/src/worker.ts","line":45,"character":12,"url":"https://github.com/MichealWayne/fe-tools/blob/88d7404/utils/packages/web-utils/src/worker.ts#L45"}],"type":{"type":"union","types":[{"type":"intrinsic","name":"string"},{"type":"reflection","declaration":{"id":1428,"name":"__type","kind":65536,"kindString":"Type literal","flags":{},"sources":[{"fileName":"packages/web-utils/src/worker.ts","line":45,"character":36,"url":"https://github.com/MichealWayne/fe-tools/blob/88d7404/utils/packages/web-utils/src/worker.ts#L45"}],"signatures":[{"id":1429,"name":"__type","kind":4096,"kindString":"Call signature","flags":{},"type":{"type":"intrinsic","name":"any"}}]}}]},"is":{"declaration":true},"location":{"query":"web-utils/src/worker.Class.WorkerPool","hash":"workerScript"},"text":{"comment":"<p>Worker 脚本路径或函数</p>\n"},"parentId":1407},{"id":1414,"name":"workers","kind":1024,"kindString":"Property","flags":{"isPrivate":true},"sources":[{"fileName":"packages/web-utils/src/worker.ts","fullFileName":"/home/runner/work/fe-tools/fe-tools/utils/packages/web-utils/src/worker.ts","line":31,"character":10,"url":"https://github.com/MichealWayne/fe-tools/blob/88d7404/utils/packages/web-utils/src/worker.ts#L31"}],"type":{"type":"array","elementType":{"type":"reference","name":"Worker","qualifiedName":"Worker","package":"typescript"}},"defaultValue":"[]","is":{"declaration":true},"location":{"query":"web-utils/src/worker.Class.WorkerPool","hash":"workers"},"text":{},"parentId":1407},{"id":1443,"name":"exec","kind":2048,"kindString":"Method","flags":{},"sources":[{"fileName":"packages/web-utils/src/worker.ts","fullFileName":"/home/runner/work/fe-tools/fe-tools/utils/packages/web-utils/src/worker.ts","line":135,"character":2,"url":"https://github.com/MichealWayne/fe-tools/blob/88d7404/utils/packages/web-utils/src/worker.ts#L135"}],"signatures":[{"id":1444,"name":"exec","kind":4096,"kindString":"Call signature","flags":{},"comment":{"summary":[{"kind":"text","text":"提交任务到工作线程池"}],"blockTags":[{"tag":"@returns","content":[{"kind":"text","text":"Promise，解析为工作线程的响应"}]}]},"parameters":[{"id":1445,"name":"data","kind":32768,"kindString":"Parameter","flags":{},"comment":{"summary":[{"kind":"text","text":"要处理的数据"}]},"type":{"type":"intrinsic","name":"any"},"text":{"comment":"<p>要处理的数据</p>\n"}}],"type":{"type":"reference","typeArguments":[{"type":"intrinsic","name":"any"}],"name":"Promise","qualifiedName":"Promise","package":"typescript"},"is":{"declaration":false},"location":{"query":"web-utils/src/worker.WorkerPool.Method.exec","hash":"exec.exec"},"text":{"comment":"<p>提交任务到工作线程池</p>\n<h5>Returns:</h5><p>Promise，解析为工作线程的响应</p>\n"},"sources":[{"fileName":"packages/web-utils/src/worker.ts","fullFileName":"/home/runner/work/fe-tools/fe-tools/utils/packages/web-utils/src/worker.ts","line":135,"character":2,"url":"https://github.com/MichealWayne/fe-tools/blob/88d7404/utils/packages/web-utils/src/worker.ts#L135"}],"parentId":1443}],"is":{"declaration":true},"location":{"query":"web-utils/src/worker.Class.WorkerPool","hash":"exec"},"text":{},"parentId":1407},{"id":1437,"name":"handleWorkerError","kind":2048,"kindString":"Method","flags":{"isPrivate":true},"sources":[{"fileName":"packages/web-utils/src/worker.ts","fullFileName":"/home/runner/work/fe-tools/fe-tools/utils/packages/web-utils/src/worker.ts","line":97,"character":10,"url":"https://github.com/MichealWayne/fe-tools/blob/88d7404/utils/packages/web-utils/src/worker.ts#L97"}],"signatures":[{"id":1438,"name":"handleWorkerError","kind":4096,"kindString":"Call signature","flags":{},"comment":{"summary":[{"kind":"text","text":"处理 Worker 错误"}]},"parameters":[{"id":1439,"name":"worker","kind":32768,"kindString":"Parameter","flags":{},"type":{"type":"reference","name":"Worker","qualifiedName":"Worker","package":"typescript"},"text":{}},{"id":1440,"name":"error","kind":32768,"kindString":"Parameter","flags":{},"type":{"type":"reference","name":"ErrorEvent","qualifiedName":"ErrorEvent","package":"typescript"},"text":{}}],"type":{"type":"intrinsic","name":"void"},"is":{"declaration":false},"location":{"query":"web-utils/src/worker.WorkerPool.Method.handleWorkerError","hash":"handleWorkerError.handleWorkerError"},"text":{"comment":"<p>处理 Worker 错误</p>\n"},"sources":[{"fileName":"packages/web-utils/src/worker.ts","fullFileName":"/home/runner/work/fe-tools/fe-tools/utils/packages/web-utils/src/worker.ts","line":97,"character":2,"url":"https://github.com/MichealWayne/fe-tools/blob/88d7404/utils/packages/web-utils/src/worker.ts#L97"}],"parentId":1437}],"is":{"declaration":true},"location":{"query":"web-utils/src/worker.Class.WorkerPool","hash":"handleWorkerError"},"text":{},"parentId":1407},{"id":1433,"name":"handleWorkerMessage","kind":2048,"kindString":"Method","flags":{"isPrivate":true},"sources":[{"fileName":"packages/web-utils/src/worker.ts","fullFileName":"/home/runner/work/fe-tools/fe-tools/utils/packages/web-utils/src/worker.ts","line":79,"character":10,"url":"https://github.com/MichealWayne/fe-tools/blob/88d7404/utils/packages/web-utils/src/worker.ts#L79"}],"signatures":[{"id":1434,"name":"handleWorkerMessage","kind":4096,"kindString":"Call signature","flags":{},"comment":{"summary":[{"kind":"text","text":"处理 Worker 消息"}]},"parameters":[{"id":1435,"name":"worker","kind":32768,"kindString":"Parameter","flags":{},"type":{"type":"reference","name":"Worker","qualifiedName":"Worker","package":"typescript"},"text":{}},{"id":1436,"name":"event","kind":32768,"kindString":"Parameter","flags":{},"type":{"type":"reference","typeArguments":[{"type":"intrinsic","name":"any"}],"name":"MessageEvent","qualifiedName":"MessageEvent","package":"typescript"},"text":{}}],"type":{"type":"intrinsic","name":"void"},"is":{"declaration":false},"location":{"query":"web-utils/src/worker.WorkerPool.Method.handleWorkerMessage","hash":"handleWorkerMessage.handleWorkerMessage"},"text":{"comment":"<p>处理 Worker 消息</p>\n"},"sources":[{"fileName":"packages/web-utils/src/worker.ts","fullFileName":"/home/runner/work/fe-tools/fe-tools/utils/packages/web-utils/src/worker.ts","line":79,"character":2,"url":"https://github.com/MichealWayne/fe-tools/blob/88d7404/utils/packages/web-utils/src/worker.ts#L79"}],"parentId":1433}],"is":{"declaration":true},"location":{"query":"web-utils/src/worker.Class.WorkerPool","hash":"handleWorkerMessage"},"text":{},"parentId":1407},{"id":1431,"name":"initialize","kind":2048,"kindString":"Method","flags":{"isPrivate":true},"sources":[{"fileName":"packages/web-utils/src/worker.ts","fullFileName":"/home/runner/work/fe-tools/fe-tools/utils/packages/web-utils/src/worker.ts","line":54,"character":10,"url":"https://github.com/MichealWayne/fe-tools/blob/88d7404/utils/packages/web-utils/src/worker.ts#L54"}],"signatures":[{"id":1432,"name":"initialize","kind":4096,"kindString":"Call signature","flags":{},"comment":{"summary":[{"kind":"text","text":"初始化工作线程池"}]},"type":{"type":"intrinsic","name":"void"},"is":{"declaration":false},"location":{"query":"web-utils/src/worker.WorkerPool.Method.initialize","hash":"initialize.initialize"},"text":{"comment":"<p>初始化工作线程池</p>\n"},"sources":[{"fileName":"packages/web-utils/src/worker.ts","fullFileName":"/home/runner/work/fe-tools/fe-tools/utils/packages/web-utils/src/worker.ts","line":54,"character":2,"url":"https://github.com/MichealWayne/fe-tools/blob/88d7404/utils/packages/web-utils/src/worker.ts#L54"}],"parentId":1431}],"is":{"declaration":true},"location":{"query":"web-utils/src/worker.Class.WorkerPool","hash":"initialize"},"text":{},"parentId":1407},{"id":1441,"name":"processQueue","kind":2048,"kindString":"Method","flags":{"isPrivate":true},"sources":[{"fileName":"packages/web-utils/src/worker.ts","fullFileName":"/home/runner/work/fe-tools/fe-tools/utils/packages/web-utils/src/worker.ts","line":115,"character":10,"url":"https://github.com/MichealWayne/fe-tools/blob/88d7404/utils/packages/web-utils/src/worker.ts#L115"}],"signatures":[{"id":1442,"name":"processQueue","kind":4096,"kindString":"Call signature","flags":{},"comment":{"summary":[{"kind":"text","text":"处理队列中的任务"}]},"type":{"type":"intrinsic","name":"void"},"is":{"declaration":false},"location":{"query":"web-utils/src/worker.WorkerPool.Method.processQueue","hash":"processQueue.processQueue"},"text":{"comment":"<p>处理队列中的任务</p>\n"},"sources":[{"fileName":"packages/web-utils/src/worker.ts","fullFileName":"/home/runner/work/fe-tools/fe-tools/utils/packages/web-utils/src/worker.ts","line":115,"character":2,"url":"https://github.com/MichealWayne/fe-tools/blob/88d7404/utils/packages/web-utils/src/worker.ts#L115"}],"parentId":1441}],"is":{"declaration":true},"location":{"query":"web-utils/src/worker.Class.WorkerPool","hash":"processQueue"},"text":{},"parentId":1407},{"id":1446,"name":"terminate","kind":2048,"kindString":"Method","flags":{},"sources":[{"fileName":"packages/web-utils/src/worker.ts","fullFileName":"/home/runner/work/fe-tools/fe-tools/utils/packages/web-utils/src/worker.ts","line":150,"character":2,"url":"https://github.com/MichealWayne/fe-tools/blob/88d7404/utils/packages/web-utils/src/worker.ts#L150"}],"signatures":[{"id":1447,"name":"terminate","kind":4096,"kindString":"Call signature","flags":{},"comment":{"summary":[{"kind":"text","text":"终止所有工作线程并释放资源"}]},"type":{"type":"intrinsic","name":"void"},"is":{"declaration":false},"location":{"query":"web-utils/src/worker.WorkerPool.Method.terminate","hash":"terminate.terminate"},"text":{"comment":"<p>终止所有工作线程并释放资源</p>\n"},"sources":[{"fileName":"packages/web-utils/src/worker.ts","fullFileName":"/home/runner/work/fe-tools/fe-tools/utils/packages/web-utils/src/worker.ts","line":150,"character":2,"url":"https://github.com/MichealWayne/fe-tools/blob/88d7404/utils/packages/web-utils/src/worker.ts#L150"}],"parentId":1446}],"is":{"declaration":true},"location":{"query":"web-utils/src/worker.Class.WorkerPool","hash":"terminate"},"text":{},"parentId":1407}],"groups":[{"title":"Constructors","children":[1408]},{"title":"Properties","children":[1426,1415,1430,1427,1414]},{"title":"Methods","children":[1443,1437,1433,1431,1441,1446]}],"sources":[{"fileName":"packages/web-utils/src/worker.ts","fullFileName":"/home/runner/work/fe-tools/fe-tools/utils/packages/web-utils/src/worker.ts","line":30,"character":13,"url":"https://github.com/MichealWayne/fe-tools/blob/88d7404/utils/packages/web-utils/src/worker.ts#L30"}],"is":{"declaration":true},"location":{"query":"web-utils/src/worker.Class.WorkerPool","hash":""},"text":{"comment":"<p>工作线程池 - 管理多个 Worker 实例</p>\n"},"parentId":1381,"hierarchy":[{"name":"WorkerPool","isTarget":true,"linkId":"1407"}]}
